[
    {
        "podcastName": "flow",
        "episode": "CBUM - Flow #319",
        "videoId": "pQSuQmUfS30",
        "categories": ["saúde", "esporte", "bodybuilder"]
    },
    {
        "podcastName": "flow",
        "episode": "RUBENS BARRICHELLO - Flow #339",
        "videoId": "4KDGTdiOV4I",
        "categories": ["esporte", "corrida"]
    },
    {
        "podcastName": "flow",
        "episode": "Pedro Willen - Flow #339",
        "videoId": "0000000",
        "categories": ["esporte", "tech"]
    },
    {
        "podcastName": "venus",
        "episode": "Pedro Santiago - Flow #339",
        "videoId": "0001230000",
        "categories": ["esporte", "tech"]
    }
]